pyimpspec/CHANGELOG.md
pyimpspec/CONTRIBUTORS
pyimpspec/COPYRIGHT
pyimpspec/LICENSE
pyimpspec/README.md
pyimpspec/__init__.py
pyimpspec/__main__.py
pyimpspec/exceptions.py
pyimpspec/mock_data.py
pyimpspec/progress.py
pyimpspec/version.py
pyimpspec/LICENSES/LICENSE-DRT-from-Loewner-framework.txt
pyimpspec/LICENSES/LICENSE-DRT-python-code.txt
pyimpspec/LICENSES/LICENSE-Elchemea Analytical.txt
pyimpspec/LICENSES/LICENSE-Jinja.txt
pyimpspec/LICENSES/LICENSE-circuitikz.txt
pyimpspec/LICENSES/LICENSE-cvxopt.txt
pyimpspec/LICENSES/LICENSE-impedance.py.txt
pyimpspec/LICENSES/LICENSE-kvxopt.txt
pyimpspec/LICENSES/LICENSE-lmfit.txt
pyimpspec/LICENSES/LICENSE-matplotlib.txt
pyimpspec/LICENSES/LICENSE-nearestSPD.txt
pyimpspec/LICENSES/LICENSE-numdifftools.txt
pyimpspec/LICENSES/LICENSE-numpy.txt
pyimpspec/LICENSES/LICENSE-odfpy.txt
pyimpspec/LICENSES/LICENSE-openpyxl.txt
pyimpspec/LICENSES/LICENSE-pandas.txt
pyimpspec/LICENSES/LICENSE-pyDRTtools.txt
pyimpspec/LICENSES/LICENSE-schemdraw.txt
pyimpspec/LICENSES/LICENSE-scipy.txt
pyimpspec/LICENSES/LICENSE-statsmodels.txt
pyimpspec/LICENSES/LICENSE-sympy.txt
pyimpspec/LICENSES/LICENSE-tabulate.txt
pyimpspec/LICENSES/LICENSE-tol_colors.txt
pyimpspec/LICENSES/LICENSE-xdg.txt
pyimpspec/LICENSES/README.md
pyimpspec/analysis/__init__.py
pyimpspec/analysis/fitting.py
pyimpspec/analysis/utility.py
pyimpspec/analysis/drt/__init__.py
pyimpspec/analysis/drt/bht.py
pyimpspec/analysis/drt/lm.py
pyimpspec/analysis/drt/mrq_fit.py
pyimpspec/analysis/drt/peak_analysis.py
pyimpspec/analysis/drt/result.py
pyimpspec/analysis/drt/tr_nnls.py
pyimpspec/analysis/drt/tr_rbf.py
pyimpspec/analysis/drt/utility.py
pyimpspec/analysis/kramers_kronig/__init__.py
pyimpspec/analysis/kramers_kronig/cnls.py
pyimpspec/analysis/kramers_kronig/exploratory.py
pyimpspec/analysis/kramers_kronig/least_squares.py
pyimpspec/analysis/kramers_kronig/matrix_inversion.py
pyimpspec/analysis/kramers_kronig/result.py
pyimpspec/analysis/kramers_kronig/single.py
pyimpspec-5.1.2.dist-info/LICENSE
pyimpspec-5.1.2.dist-info/METADATA
pyimpspec-5.1.2.dist-info/WHEEL
pyimpspec-5.1.2.dist-info/entry_points.txt
pyimpspec-5.1.2.dist-info/top_level.txt
pyimpspec-5.1.2.dist-info/RECORD
