Metadata-Version: 2.2
Name: pyimpspec
Version: 5.1.2
Summary: A package for parsing, validating, analyzing, and simulating impedance spectra.
Home-page: https://vyrjana.github.io/pyimpspec
Author: pyimpspec developers
License: GPLv3
Project-URL: Documentation, https://vyrjana.github.io/pyimpspec/api/
Project-URL: Source Code, https://github.com/vyrjana/pyimpspec
Project-URL: Bug Tracker, https://github.com/vyrjana/pyimpspec/issues
Classifier: Intended Audience :: Science/Research
Classifier: License :: OSI Approved :: GNU General Public License v3 (GPLv3)
Classifier: Operating System :: MacOS
Classifier: Operating System :: Microsoft :: Windows
Classifier: Operating System :: POSIX :: Linux
Classifier: Programming Language :: Python :: 3.10
Classifier: Programming Language :: Python :: 3.11
Classifier: Programming Language :: Python :: 3.12
Classifier: Programming Language :: Python :: 3.13
Classifier: Programming Language :: Python :: 3 :: Only
Classifier: Topic :: Scientific/Engineering :: Chemistry
Classifier: Topic :: Scientific/Engineering :: Physics
Classifier: Topic :: Scientific/Engineering
Requires-Python: >=3.10
License-File: LICENSE
Requires-Dist: Jinja2~=3.1
Requires-Dist: lmfit~=1.3
Requires-Dist: matplotlib~=3.10
Requires-Dist: numdifftools~=0.9
Requires-Dist: numpy~=2.2
Requires-Dist: odfpy~=1.4
Requires-Dist: openpyxl~=3.1
Requires-Dist: pandas~=2.2
Requires-Dist: schemdraw~=0.19
Requires-Dist: scipy~=1.15
Requires-Dist: statsmodels~=0.14
Requires-Dist: sympy~=1.13
Requires-Dist: tabulate~=0.9
Requires-Dist: xdg~=6.0
Provides-Extra: cvxopt
Requires-Dist: cvxopt~=1.3; extra == "cvxopt"
Provides-Extra: kvxopt
Requires-Dist: kvxopt~=1.3; extra == "kvxopt"
Provides-Extra: dev
Requires-Dist: build~=1.2; extra == "dev"
Requires-Dist: flake8~=7.1; extra == "dev"
Requires-Dist: setuptools~=75.8; extra == "dev"
Requires-Dist: sphinx~=8.2; extra == "dev"
Requires-Dist: sphinx-rtd-theme~=3.0; extra == "dev"
Dynamic: author
Dynamic: classifier
Dynamic: description
Dynamic: description-content-type
Dynamic: home-page
Dynamic: license
Dynamic: project-url
Dynamic: provides-extra
Dynamic: requires-dist
Dynamic: requires-python
Dynamic: summary
